git_networkx/__init__.py
git_networkx/exceptions.py
git_networkx/git_functions.py
git_networkx/git_graph_class.py
git_networkx/git_networkx.py
git_networkx/git_node.py
git_networkx-2.3.0.dist-info/LICENSE.txt
git_networkx-2.3.0.dist-info/WHEEL
git_networkx-2.3.0.dist-info/METADATA
git_networkx-2.3.0.dist-info/RECORD
