Metadata-Version: 2.1
Name: git-networkx
Version: 2.3.0
Summary: Git graph to networkx
Home-page: https://github.com/CircArgs/git-graph
License: MIT
Keywords: git,directed,acyclic,graph,dag,dot
Author: Nick Ouellet
Author-email: nick@ouellet.dev
Requires-Python: >=3.6,<4.0
Classifier: License :: OSI Approved :: MIT License
Classifier: Operating System :: OS Independent
Classifier: Programming Language :: Python :: 3
Classifier: Programming Language :: Python :: 3.6
Classifier: Programming Language :: Python :: 3.7
Classifier: Programming Language :: Python :: 3.8
Requires-Dist: networkx (>=2.4,<3.0)
